be/__init__.py
be/api/__init__.py
be/api/demand.py
be/api/goals.py
be/api/matches.py
be/api/supply.py
app.json
avyas_aurica_base_apps_demand_supply-1.0.1.dist-info/METADATA
avyas_aurica_base_apps_demand_supply-1.0.1.dist-info/WHEEL
avyas_aurica_base_apps_demand_supply-1.0.1.dist-info/RECORD
