Metadata-Version: 2.4
Name: avyas-aurica-base-apps-demand-supply
Version: 1.0.1
Summary: Aurica app: demand-supply
Requires-Python: >=3.11
Requires-Dist: fastapi>=0.104.0
Requires-Dist: uvicorn>=0.24.0
